README.md
setup.py
src/languageformatters/__init__.py
src/languageformatters/format_tools.py
src/languageformatters/json_formatter.py
src/languageformatters.egg-info/PKG-INFO
src/languageformatters.egg-info/SOURCES.txt
src/languageformatters.egg-info/dependency_links.txt
src/languageformatters.egg-info/not-zip-safe
src/languageformatters.egg-info/top_level.txt