Metadata-Version: 2.1
Name: languageformatters
Version: 0.0.4
Summary: A collection of formatters for various languages.
Home-page: https://gitlab.com/mburkard/language-formatters
Author: Matthew Burkard
Author-email: matthewjburkard@gmail.com
License: GNU General Public License v3 (GPLv3)
Platform: UNKNOWN
Classifier: Programming Language :: Python :: 3
Classifier: License :: OSI Approved :: GNU General Public License v3 (GPLv3)
